rewards_experimental/__init__.py
rewards_experimental/agent.py
rewards_experimental/config.py
rewards_experimental/models.py
rewards_experimental/multiagent.py
rewards_experimental/trainer.py
rewards_experimental/utils.py
rewards_experimental/workflow.py
rewards_experimental-0.0.2.dist-info/METADATA
rewards_experimental-0.0.2.dist-info/WHEEL
rewards_experimental-0.0.2.dist-info/RECORD
